Metadata-Version: 2.4
Name: rail-engine
Version: 0.1.6
Summary: Python SDK for Railtown AI Rail Engine - Retrieval
Author-email: Railtown AI <support@railtown.ai>
License: MIT
Project-URL: Homepage, https://github.com/railtownai/railengine-sdk
Project-URL: Documentation, https://github.com/railtownai/railengine-sdk
Project-URL: Repository, https://github.com/railtownai/railengine-sdk
Keywords: railtown,rail-engine,retrieval,sdk
Classifier: Development Status :: 4 - Beta
Classifier: Intended Audience :: Developers
Classifier: License :: OSI Approved :: MIT License
Classifier: Programming Language :: Python :: 3
Classifier: Programming Language :: Python :: 3.10
Classifier: Programming Language :: Python :: 3.11
Classifier: Programming Language :: Python :: 3.12
Requires-Python: >=3.10
License-File: LICENSE
Requires-Dist: httpx>=0.24.0
Requires-Dist: pydantic>=1.10.0
Dynamic: license-file
